{
  "datas": [
    {
      "id": "0",
      "icon": "Warrior_Stand",
      "name": "워리어",
      "buff": "공격 속도 10% 증가",
      "locktext": "최초 접속 시 해금",
      "color": [ "255", "176", "64" ]
    },
    {
      "id": "1",
      "icon": "Thief_Stand",
      "name": "도적",
      "buff": "투사체/관통 1개 증가",
      "locktext": "1회 이상 게임 플레이 해금",
      "color": [ "30", "111", "80" ]
    },
    {
      "id": "2",
      "icon": "Saint_Stand",
      "name": "성직자",
      "buff": "데미지 10% 증가",
      "locktext": "최초 생존 시 해금",
      "color": [ "180", "180", "180" ]
    },
    {
      "id": "3",
      "icon": "Captain_Stand",
      "name": "캡틴",
      "buff": "이동 속도 20% 증가",
      "locktext": "200킬 이상 시 해금",
      "color": [ "224", "116", "56" ]
    },
    {
      "id": "4",
      "icon": "Knight_Stand",
      "name": "흑기사",
      "buff": "기본 체력 3배",
      "locktext": "500킬 이상 시 해금",
      "color": [ "196", "36", "48" ]
    },
    {
      "id": "5",
      "icon": "Mage_Stand",
      "name": "리치",
      "buff": "데미지 3배",
      "locktext": "조건 비공개",
      "color": [ "0", "105", "170" ]
    }
  ]
}